{
  "passage_id": "CNTS-00060911477_111_112-0",
  "metadata": {
    "doc_id": "CNTS-00060911477",
    "doc_type": "도서",
    "doc_name": "정념의 인식론",
    "author": "그레마스, A.J.",
    "publisher": "[발행처 불명]",
    "published_year": "2013",
    "kdc_label": "형이상학",
    "kdc_code": "115"
  },
  "chapter": "2. 유약한 세계",
  "passage": "일종의 포기인 이러한 제스처는 뉴욕 미니멀리즘 안 어디에서든지 나타난다. 바바라 로즈는 다음과 같이 언급한다. \"내가 언급했던 그 예술은 분명히 거절과 포기의 부정적인 예술로 존재한다.\" 미니멀리스트 작품의 바로 그 문체론적 적나라함과 표출 형식의 빈곤은 관찰자에게 충격으로 해석되고, 관찰자가 그 구성적 변화과정을 반성하도록 만든다. 소정의 예기에 대한 관찰자의 평범한 지평에서 보면, 이러한 종류의 작품과 직면했을 때 관찰자의 반응은 처음에 복합적인 것이 간섭했던, 환원의 가혹한 약동을 통하여 그것에 얽히고설킴의 네거티브 필름 막을 붙였던, 어떤 무엇의 모습으로 반드시 나타난다.",
  "summary": "미니멀리시트 작품의 문체론적 적나라함과 표출 방식은 관찰자에게 충격으로 해석되며, 구성적 변화과정을 반성하게 한다. 이때 관찰자의 반응은 어떤 무엇의 모습으로 반드시 나타난다."
}