{
  "passage_id": "CNTS-00118880770_58",
  "metadata": {
    "doc_id": "CNTS-00118880770",
    "doc_type": "도서",
    "doc_name": "2015 베니스비엔날레 국제미술전 한국관 백서",
    "author": "한국문화예술위원회",
    "publisher": "한국문화예술위원회",
    "published_year": "2016",
    "kdc_label": "예술",
    "kdc_code": "600"
  },
  "chapter": null,
  "passage": "결국 현재에 대해 무언가를 발언하고 싶은 사람들이 미래를 언급한다고 생각합니다. 괴이한 상황들이 만연하는 현재의 상황과 예술계도 지난 10여 년간 극도로 상업화되면서 공공 미술관에서 가장 고민하는 것은 이렇게 많은 개인의 후원을 받고 기업체의 지원을 받고 사적인 재산을 받아서 전시하는 우리가 얼마나 공공성을 유지할 수 있는가를 고민하고 있습니다. 이러한 여러 가지 지점들을 생각했을 때 한국의 미술가들이 세계 미술과 직접 교류를 하면서 아주 다양한 목소리를 이미 내고 있단 말이죠. 그런 작가분들 중에서 한국관이라는 플랫폼을 통해서 제가 공감하고 확성기처럼 더 강조하고 싶은 부분들을 다루고 계신 작가로서 문경원, 전준호 작가분들을 초대하게 되었습니다.",
  "summary": "공공 미술관의 극심한 상업화로 이런 전시 활동이 과연 공공성을 유지할 수 있는가를 고민하게 되었습니다. 이에 대해 한국관 플랫폼으로  목소리를 내고 계신  문경원, 전준호 작가분들을 초대했습니다."
}