{
  "passage_id": "CNTS-00061102375_77_77-0",
  "metadata": {
    "doc_id": "CNTS-00061102375",
    "doc_type": "도서",
    "doc_name": "외솔 최현배 선생의 학문과 인간",
    "author": "국립국어연구원",
    "publisher": "국립국어원",
    "published_year": "1993",
    "kdc_label": "한국어",
    "kdc_code": "710"
  },
  "chapter": "우리 말본'의 씨갈 4 4.3",
  "passage": " 감동사는 절이나 문장 앞에서 그것을 꾸미는 품사로 정의하였다. 감동사를 '꾸밈씨'로 분류하였으나 문장의 조직에는 큰 관계가 없는 독립적인 성분임을 언급하고 있어 그 분류에 문제점이 있음을 스스로 인정하고 있다. 어미나 조사 그리고 어조에 의한 느낌을 나타내는 것은 감동사가 아니라고 하면서도 체언인 '이놈, 요놈, 저놈, 그놈' 등과 용언인 '옳다, 옳지, 좋다, 잘한다, 버텨라, 뽐내라' 등을 감동사에 포함한 것은 잘못된 것이다. 그 밖에 '왜, 정말, 글쎄, 어디' 등은 부사로도 분류되는 것이다.\n 감동사는 놀람, 기쁨 같은 순연한 감정을 나타내는 감정적 감동사와 꾀임, 부름 같은 의지의 앞머리를 나타내는 의지적 감동사로 분류하였다. 현행 학교 문법에서도 감탄사는 감정 감탄사와 의지 감탄사로 분류하고 있다. 그러나 그 의미를 기준으로 감정적 감동사는 기쁨, 성냄, 슬픔 ,걱정, 한숨 등 25가지로 분류하고 의지적 감동사는 단념, 주의, 부름, 대답 등 9가지로 분류한 것은 의미를 기준으로 한 분류의 극단적인 경우이다. ",
  "summary": "감동사는 절과 문장 앞에서 꾸미는 품사로 독립적인 성분이다. 체언과 용언 일부를 감동사에 넣은 것은 잘못됐다. 그 밖에 일부는 부사로도 분류된다. 감동사는 감정적, 의지적 감동사로 나뉘는데 의미를 기준으로 극단적인 분류를 했다. 현행 학교 문법에서는 감정, 의지 감탄사로 분류한다"
}