{
  "passage_id": "CNTS-00061098076_114",
  "metadata": {
    "doc_id": "CNTS-00061098076",
    "doc_type": "도서",
    "doc_name": "아시아 영화산업 현황과 지역내 협력방안 연구",
    "author": "김혜준",
    "publisher": "영화진흥위원회",
    "published_year": "2000",
    "kdc_label": "공연예술 및 매체예술",
    "kdc_code": "680"
  },
  "chapter": null,
  "passage": "이처럼 1999년 일본영화계는 한마디로 메이저의 하락과 독립제작 영화들의 고군분투한 한 해로 정의 내릴 수 있다. 일본의 메이저가 제작에서 멀어진 것은 이미 오래 전의 일이지만, 위에서 살펴본 것처럼 블록 부킹의 포기(물론 도호와 도에이는 여전히 블록 부킹 시스템을 사용하고 있다), 시네마 콤플렉스의 등장 등을 통해 배급과 상영에 있어서도 변화를 보이고 있다. 이것은 메이저의 역할 변화가 TV 등 새로운 매체의 영화제작 참여, 독립제작영화의 활성화 등 새로운 일본영화 판도 형성에 기여하고 있음을 나타내고 있다. 이와 같은 일본 영화의 새 지도는 95년 이후 일본 영화들의 특징들을 살펴본 앞의 글과 많은 공통점을 보이고 있다. 그럼 나아가 이처럼 1999년을 포함한 최근 5년간의 일본영화계의 특징들을 통해, 실제로 일본영화의 제작, 배급, 상영의 시스템 속에서 메이저 영화와 독립제작 영화들이 어떻게 역할 분담을 하고 있는지 살펴보도록 하자.",
  "summary": "일본의 메이저는 TV 등 새로운 매체의 영화제작 참여, 독립제작영화의 활성화 등 새로운 판도 형성에 기여하고 있다. 최근 일본영화계의 특징들을 통해 일본영화 시스템 속 메이저 영화와 독립제작 영화들의 역할 분담에 대해 살펴보자."
}