{
  "passage_id": "CNTS-00120007336_30",
  "metadata": {
    "doc_id": "CNTS-00120007336",
    "doc_type": "도서",
    "doc_name": "행복한 교육",
    "author": "교육부",
    "publisher": "교육부",
    "published_year": "2015",
    "kdc_label": "교육학",
    "kdc_code": "370"
  },
  "chapter": null,
  "passage": "대회는 크게 참가팀별 발표와 그에 대한 타 참가팀의 질의 및 답변으로 진행되었다. 각 참가팀은 연극, 뉴스, 토론, 동영상 등의 자유로운 형식을 활용하여 자신들의 탐구결과를 발표했다. 특히, 중학생 부문에 참가하여 은상을 수상한 ‘눈꽃두둥(대전, 대전지족중)’ 팀은 전통의상인 한복을 입고 나와 ‘역사를 둘러싼 한·중·일 갈등’에 대해서 발표하며, 자신들의 장래희망에 따른 역사문제 해결방안을 발표하여 눈길을 끌었고, 고등학생부문에 참가하여 동상을 수상한 ‘온새미로(경기, 세마고)’ 팀은 뉴스 형식을 통해 현재 통일을 위해 필요한 노력에 대해 발표하였고, 아울러 남북한의 진정한 통합을 위한 통합 국어교육을 제안하였다.",
  "summary": "대회는 한 참가팀이 발표를 하면 타 참가팀이 그에 대해 질문하고 답변하는 식으로 진행되었다. 각 참가팀은 자유로운 형식으로 탐구결과를 발표했다."
}