{
  "passage_id": "CNTS-00061098099_173",
  "metadata": {
    "doc_id": "CNTS-00061098099",
    "doc_type": "도서",
    "doc_name": "아시아·태평양 지역 한국영화 진출현황연구",
    "author": "박희성",
    "publisher": "영화진흥위원회",
    "published_year": "2003",
    "kdc_label": "공연예술 및 매체예술",
    "kdc_code": "680"
  },
  "chapter": null,
  "passage": "외국영화 쿼터가 없어지면서 멀티플렉스는 더욱 급격하게 늘어나 1997년 13개 스크린,  2,089개 규모의 장춘학자(창춘슈에저)영성(長春學者影城)은 타이베이에만 5개의 체인을 건립하였고 1998년 총독(쫑두, 總督), 수도(셔우두, 首都) 극장이 금상장(진샹쟝, 金像獎) 극장과 합쳐 총독/금상장영성으로 신장개업 하는가 하면, 롱샹은 1997년 브로드웨이(바이라오후이, 百老匯)영성, 가년화(지아엔화, 嘉年華)영성 등을 열었다. 이러한 멀티플렉스 건설 붐은 해안지대로 옮아가는 현상을 보이고 있는데, 타이난에 국빈영성이 7개 스크린에 1,200개 좌석 규모로 개관하는 등 타이베이를 넘어서 점차 확대되고 있다.",
  "summary": "대만에서는 외국영화 쿼터가 사라지고 1997년 , 1998년 멀티플렉스가 급격하게 증가하였다."
}