{
  "passage_id": "PCY_201611170529215831_5",
  "metadata": {
    "doc_id": "PCY_201611170529215831",
    "doc_type": "도서",
    "doc_name": "2016~2060년 NABO 장기 재정전망",
    "author": null,
    "publisher": "국회예산정책처",
    "published_year": "2016",
    "kdc_label": "기획재정",
    "kdc_code": "300"
  },
  "chapter": null,
  "passage": "본 전망에서는 2011년 중위가정을 통한 장래추계를 인구전망의 전제로 한다. 통계청 장래인구추계의 신뢰도가 높은 것으로 평가됨에도 불구하고, 미래 인구증가에 영향을 미칠 다양한 가능성은 미리 결정할 수 없는 것이므로, 인구추계는 상당한 불확실성의 요인을 내포하고 있다. 따라서 본 전망은 통계청의 중위 인구 전망을 채택하였다. 통계청의 2011년 중위 인구전망에 따르면, 총인구는 2010년 4,941만명에서 2030년 5,216만명으로 정점에 도달 후 2040년 5,109만명, 2050년 4,812만명, 그리고 2060년에 4,396만명까지 감소되는 것으로 전망되었다. 즉, 총인구 증가율은 2010년 0.46%에서 둔화되어 2031년부터 마이너스(－)로 전환되고 2060년에는 －1.0% 수준에 도달하는 것으로 전망되었다.",
  "summary": "통계청의 2011년 중위 인구 전망에서는 총인구가 2010년부터 증가해 2030년에 정점 도달 후, 지속적으로 감소해 2060년에는 총인구 증가율이 -1%의 수준에 도달할 것으로 전망했다."
}