{
  "passage_id": "PCY_201502050914405781_42",
  "metadata": {
    "doc_id": "PCY_201502050914405781",
    "doc_type": "도서",
    "doc_name": "물류기금의 도입타당성 검토 및 조성방안 연구",
    "author": null,
    "publisher": "한국교통연구원",
    "published_year": null,
    "kdc_label": "물류등기타",
    "kdc_code": "300"
  },
  "chapter": null,
  "passage": "경상사업은 관광진흥기반 확충, 관광사업 육성, 외래관광객 유치 등 3부문으로 구성되어 있다. 민간단체 및 지자체를 지원 대상으로 하고 있다. 관광진흥기반 확충사업은 국제경쟁력을 갖춘 고품격․지역 특화 관광 인프라 확충 및 내실화 도모가 핵심 내용이다. 관광산업 육성사업은 우수 관광상품 개발 및 보급, 지역 특화 관광자원의 집중 홍보 및 마케팅, 소외계층의 복지관광 추진, 관광숙박시설 건설 지원 등을 포함한다. 마지막으로 외래관광객 유치 사업은 외래관광객 유치 기반 조성, 외래객 유치 여행상품의 가격 경쟁력 약화 및 관광수지 적자 심화 대응 방안 마련, 관광문화 관련 연계 서비스 제공의 핵심 거점 마련, 고부가가치 MICE 산업 육성, 문화원 거점의 지역별 사업 및 문화 사업 추진 등을 포함한다. 융자사업은 관광사업체 또는 관광사업 예정자를 대상으로 관광숙박시설, 국민관광진흥시설의 건설 및 개보수, 관광사업체 운영 등에 융자지원을 한다. 융자는 한국산업은행 등 16개 시중은행에서 취급하고 있다.",
  "summary": "경상사업은 지역 관광 인프라 확충을 위한 관광진흥기반 확충, 우수 관광상품 개발과 홍보를 포함하는 관광사업 육성, 외래관광객의 유치 기반을 조성하는 외래관광객 유치사업 등 세 부문으로 구성된다. 융자사업은 시중은행이 관광사업체를 대상으로 융자를 지원하는 사업이다. "
}