{
  "passage_id": "PCY_201501290926043581_3",
  "metadata": {
    "doc_id": "PCY_201501290926043581",
    "doc_type": "도서",
    "doc_name": "2014 보육정책의 성과와 과제",
    "author": null,
    "publisher": "육아정책연구소",
    "published_year": null,
    "kdc_label": "유아및초·중등교육",
    "kdc_code": "300"
  },
  "chapter": null,
  "passage": "한편, 본 연구 과제는 매년 시급하게 현황 파악이 요구되는 정책이나 제도에 대해 제도의 개선이나 효율적 운영에 도움을 주고자 심층분석을 실시하고 있다. 2014년에는 2013년 전연령․전소득계층의 영유아에 보편화된 ‘양육수당’에 대한 국민 인식과 만족도를 점검하고 향후 제도 설계 변경 시 효과를 예측하기 위해 ‘양육수당’에 대한 심층 분석을 실시하였다. 이와 함께 2013년 11월 시범사업 실시 후 2014년 4월부터 전국적으로 확대 도입된 ‘어린이집 입소대기 관리시스템’도 제도 도입 초기 만족도 조사와 개선 사항 도출로 제도 안착을 지원하고자 심층주제로 선정하였다.",
  "summary": "본 연구에서는 양육수당과 어린이집 입소대기 관리시스템을 심층 분석 주제로 선정하였다."
}