{
  "passage_id": "PCY_201909180456259121_0",
  "metadata": {
    "doc_id": "PCY_201909180456259121",
    "doc_type": "도서",
    "doc_name": "2017-2018년 국내 중증열성혈소판감소증후군(SFTS) 실험실 검사 현황",
    "author": null,
    "publisher": "질병관리본부",
    "published_year": "2019",
    "kdc_label": "보건의료",
    "kdc_code": "500"
  },
  "chapter": null,
  "passage": "중증열성혈소판감소증후군( Severe fever with thrombocytopenia syndrome, SFTS)은 주로 작은소피참진드기(Haemaphysalis longicornis)가 매개하는 바이러스성 질환이다. 중증열성혈소판감소증후군 바이러스(Severe fever with thrombocytopenia syndrome virus, SFTSV)는 Phenuiviridae과 Phlebovirus 속에 속하며, 2011년 중국에서 처음 환자 발생이 보고되었고, 이어서 일본, 한국에서도 환자 발생이 보고되었다. SFTS의 주요 증상은 고열, 혈소판 감소, 구토, 설사 등이 나타나고, 중증인 경우 신경계 증상, 출혈 증상, 다발성 장기 손상으로 인해 6∼30%의 사망률을 보인다.",
  "summary": "중증열성혈소판감소증후군은 바이러스성 질환으로 2011년 중국을 시작으로 일본, 한국에서도 환자가 나타났다. 주로 고열, 혈소판 감소, 구토, 설사 등을 동반하며 중증인 경우 사망률이 6∼30%에 이른다. "
}