{
  "passage_id": "PCY_201808240406143571_19",
  "metadata": {
    "doc_id": "PCY_201808240406143571",
    "doc_type": "도서",
    "doc_name": "근로시간이 주관적 건강상태에 미치는 영향 : 내생적 순서형 프로빗 모형을 중심으로",
    "author": "유혜림",
    "publisher": "한국노동연구원",
    "published_year": "2018",
    "kdc_label": "고용노동",
    "kdc_code": "300"
  },
  "chapter": null,
  "passage": "셋째, 노동관련 변수인 임금, 교육, 직업 및 종사상의 지위에 대해 살펴보면, 임금수준과 교육은 통계적으로 유의하였다. 임금변수 추정계수는 양(+)으로 나타나 근로자의 소득이 증가할수록 가장 높은 범주인 ‘아주 건강하다’로 응답할 확률이 통계적으로 유의하게 증가한다. 교육의 경우, 고졸 미만을 기준으로 학력이 높을수록 건강상태가 더 높은 건강수준을 가질 확률이 증가한다. 직업변수의 경우 통계적으로 유의하지 않았으며, 종사상의 지위 측면에서는 상용직에 비해 임시직, 일용직의 건강상태가 가장 낮은 범주에 속할 확률이 증가하는 것으로 나타났다",
  "summary": "임금, 교육은 통계적으로 비례하여 증가한다. 직업 및 종사자의 지위는 상용직에 비해 임시직, 일용직의 건강상태가 낮을 확률이 크다."
}