{
  "passage_id": "PCY_201610210307087901_55",
  "metadata": {
    "doc_id": "PCY_201610210307087901",
    "doc_type": "도서",
    "doc_name": "원자력발전의 경제적·사회적 비용을 고려한 적정 전원믹스 연구(3차년도)",
    "author": null,
    "publisher": "에너지경제연구원",
    "published_year": "2015",
    "kdc_label": "에너지및자원개발",
    "kdc_code": "300"
  },
  "chapter": null,
  "passage": "먼저 제7차 전력수급계획에 신규로 반영된 발전기 목록을 입력자료 에 포함해야 한다. 신규 발전기 입력자료 구축과정에서 주의해야 할 점은 제6차 전력수급계획에 기반영된 발전기들 중 많은 수가 건설계획이 변경되었다는 점이다. 신규 발전기의 진입 시기 정보와 아울러 중요한 사항이 기존 발전기의 폐지 시기이다. 제7차 전력수급계획에 서는 설비용량 1,500MW 원전 2기가 신규 설비로 반영되어 2027년과 2028년에 시장에 진입할 것으로 전망하고 있으며, 총 6,760MW의 노후 설비가 2029년까지 단계적으로 폐지될 것으로 계획하고 있다. 연 도별 발전설비 건설계획은 제7차 전력수급계획에서 제시하고 있는 일 정표를 준용하여 모형의 입력 자료에 반영한다(제7차 전력수급기본계획(2015~2029), 2015.7, pp 68~76 참고).",
  "summary": "제7차 전력수급계획에 신규 반영된 발전기 목록을 입력자료에 포함해야 하는데, 이 때 제6차 전력수급계획에 반영된 발전기들의 건설계획이 변경되었다는 점을 주의하여야 한다."
}