{
  "passage_id": "PCY_201506230911026891_42",
  "metadata": {
    "doc_id": "PCY_201506230911026891",
    "doc_type": "도서",
    "doc_name": "오바마 행정부의 대중동 정책: 아시아 재균형 정책과의 상관성",
    "author": null,
    "publisher": "국립외교원",
    "published_year": null,
    "kdc_label": "외교",
    "kdc_code": "300"
  },
  "chapter": null,
  "passage": "그러나 이라크와 아프가니스탄에서의 민주주의 이행 프로젝트는 성공적이지 않았다. 오히려 역설적으로 이란이 경제제재 하에서도 자기 위치를 상실하지 않고 나름대로의 안정적 선거 시스템을 가동하면서 이란의 신정주의 혁명의 이념이 이라크와 아프가니스탄으로 확대되는 일이 일어났다. 즉 시아파 다수국가인 이라크에서 이란 견제 세력보다 이란과 우호 관계를 유지하자는 시아파 지도자들이 나오기 시작했던 것이다. 아프가니스탄에서도 카르자이 정부가 미국과 각을 세우고, 미·파키스탄 관계가 극도로 악화되기 시작하자 이란·아프가니스탄·파키스탄 삼자 정상회담까지 개최하면서 미국 견제에 나서기 시작했다.",
  "summary": "이라크에서 이란과 우호관계를 가지자는 지도자들이 나오고 아프가니스탄 정부도 미국과 각을 세우는 등 이라크와 아프가니스탄에서의 민주주의 이행 프로젝트는 성공적이지 않았다."
}