{
  "passage_id": "PCY_201910040522568331_12",
  "metadata": {
    "doc_id": "PCY_201910040522568331",
    "doc_type": "도서",
    "doc_name": "되돌아보는 대한민국 전자정부 이야기 23선 (23 Unveiled Stories in Korean e-Gov)",
    "author": null,
    "publisher": "행정안전부",
    "published_year": "2017",
    "kdc_label": "국정운영",
    "kdc_code": "300"
  },
  "chapter": null,
  "passage": "정부는 국회에서 「전자정부법」이 통과되자 2001년 6월 30일에 대통령령 제17271호로 시행령을 제정하고, 2001년 7월 1일부터 시행에 들어갔다. 당시 행정자치부는 이러한 「전자정부법」의 제정 이유를 ‘21세기 지식정보화시대를 맞이하여 정보기술(IT)과 더불어 정부가 일하는 방식의 혁신을 결합하여 정부경쟁력의 향상과 대민서비스의 개선이라는 전자정부의 비전 구현을 뒷받침하기 위함ʼ이라고 밝혔다. 총 7개의 장으로 구성된 「전자정부법」은 총칙, 전자정부서비스의 제공 및 활용, 전자적 행정관리, 행정정보의 공동이용, 전자정부 운영기반의 강화, 전자정부 구현을 위한 시책 등의 추진 및 벌칙에 관한 내용을 담고 있다. 이 법은 이제까지 크게 네 차례의 주요 개정을 거쳤으며 앞으로도 시대변화에 따라 지속적으로 개정될 전망이다.",
  "summary": "2001년 7월 1일부터 시행된 「전자정부법」은 정보기술과 업무 방식의 혁신을 결합하여 정부경쟁력의 향상과 대민서비스를 개선하기 위해 제정되어 네 차례 주요 개정을 거쳤으며 앞으로도 시대변화에 맞추어 개정될 예정이다."
}