{
  "passage_id": "PCY_201610210336527441_41",
  "metadata": {
    "doc_id": "PCY_201610210336527441",
    "doc_type": "도서",
    "doc_name": "2016년 기후변화협약(UNFCCC) 다자평가 대응방안 연구 : 우리나라 감축행동공유(FSV) 대응방안",
    "author": null,
    "publisher": "에너지경제연구원",
    "published_year": "2016",
    "kdc_label": "에너지및자원개발",
    "kdc_code": "300"
  },
  "chapter": null,
  "passage": "지구적 차원의 형평성을 평가하기 위해서는 첫째, 2020년의 세계 기준 배출량(BAU)을 설정하고, 유엔의 기후변화협약과 파리협정이 추구하고 있는 산업화 이전 대비 2도 이내 지구 온도 상승을 달성하기 위한 경로를 설정하여, 기준 배출량과 2도 달성 경로와의 차이를 지구적 차원의 온실가스 감축량으로 산정하게 된다. 둘째, 각국의 형평성을 정의하기 위해 과거와 미래의 누적 온실가스 배출량을 책임(responsibility) 변수로 정의하고 소득수준을 능력(capacity) 변수로 정의하며, 책임과 능력에 가중치를 부여하여 각국의 형평성 지수를 설정하게 된다. 셋째, 2020년에 세계가 2도 상승 목표를 달성할 경우 감축해야 할 감축량을 산정하고 여기에 각국의 형평성 지수를 곱하여 각국이 담당해야 할 형평적인 감축량을 계산하게 된다. 이러한 과정을 거쳐서 2020년의 형평성에 입각한 감축량과 각국의 2020년 감축 목표의 감축량을 비교하면 감축 목표의 의욕적인 수준을 평가할 수 있게 된다. 2020년 감축 목표의 감축량이 형평성 측면에서 계산된 감축량에 비해 많으면 온실가스 감축 목표가 의욕적인 수준이며, 반대로 감축량에 비해 낮으면 감축 목표가 의욕적이지 않는 수준으로 평가된다.",
  "summary": "지구적 관점에서 형평성 평가를 위해 첫째, 산업화 이전과 대비, 지구온도 2도 상승 달성을 위해 지구차원의 온실가스 감축량으로 산출한다. 둘째, 누적 온실가스 배출량을 책임 변수, 소득수준을 능력 변수로 하여 각국의 형평성 지수를 설정한다. 셋째, 감축해야 할 양을 산출하고 각국가가 감당할 형평적인 감축량을 계산하게 된다."
}