{
  "passage_id": "PCY_201612021124245581_1",
  "metadata": {
    "doc_id": "PCY_201612021124245581",
    "doc_type": "도서",
    "doc_name": "유럽의 디지털 사회혁신 정책과 현황",
    "author": null,
    "publisher": "과학기술정책연구원",
    "published_year": "2016",
    "kdc_label": "과학기술진흥",
    "kdc_code": "500"
  },
  "chapter": null,
  "passage": "국내에서도 과학기술정책연구원(STEPI), 한국정보화진흥원(NIA), 한국전자통신연구원(ETRI), 서울 디지털 재단, 비영리 IT 지원 센터 등이 모여 DSI 의제의 논의가 시작되고 있다. 그러나 유럽의 DSI 정책에 대한 관련 정보가 부족한 실정이다. 이에, 본 보고서에서는 디지털 사회 혁신을 가장 앞장서서 주창하고 있는 유럽연합의 DSI 정책 연구의 흐름과 DSI 확산에 기여하고 있는 중간지원기관을 간략히 살펴본다. 2절에서는 유럽연합의 사회혁신 정책의 시작과 발전과정, 3절에서는 유럽 연합을 중심으로 만들어진 DSI의 정의와 지원 정책 현황을 간략히 살펴본다. 또한 본 연구의 사례조사로 채택된 디지털 소셜벤처 엑셀러레이터가 운영 중인 영국의 사회혁신 관련 지원정책도 간략히 소개된다. 4절에서는 DSI 중간지원기관의 역할과 조직의 유형을 간단히 소개하고, 5절에서는 DSI 중간지원기관 중 디지털 소셜벤처 엑셀러레이터 두 곳의 사례를 살펴본다. 이 두 사례의 연구를 통해 디지털 소셜벤처 엑셀러레이터가 기존 IT 스타트업 엑셀러레이터와 구별되는 점을 파악하여, DSI 중간지원 기관만으로서 필요한 역량과 제반 조건 등을 토론해본다. 마지막으로 6절에서는 이상의 사례 연구를 기반으로 향후 진행해야할 국내 DSI정책연구의 방향을 제언한다.",
  "summary": "유럽연합의 DSI 정책 관련 정보가 부족한 실정이기 때문에 본 보고서에서는 디지털 사회혁신을 가장 앞장서서 주장하고 있는 유럽의 DSI 정책 연구의 흐름과 DSI 확산에 이바지하고 있는 중간지원기관을 간단하게 살펴본다."
}