{
  "passage_id": "PCY_201510300112334281_38",
  "metadata": {
    "doc_id": "PCY_201510300112334281",
    "doc_type": "도서",
    "doc_name": "KDI Journal of Economic Policy=韓國開發硏究",
    "author": null,
    "publisher": "한국개발연구원\t",
    "published_year": "2015",
    "kdc_label": "금융",
    "kdc_code": "300"
  },
  "chapter": null,
  "passage": "실증분석모형의 도출과정을 소개하기에 앞서, 해당 모형에 대한 이해를 돕기 위해 Mankiw and Reis(2002)가 제시한 정보경직성 모형의 주요 특징을 간략히 설명하고자 한다. 잘 알려진 바와 같이, 해당 모형에서 경제주체는 정보획득비용으로 인해 의사결정에 필요한 정보를 상시적으로 갱신할 수 없고, Calvo(1983)에서와 유사하게 매기마다 일정한 확률로 정보 갱신의 기회를 획득하는 것으로 가정된다. 또한 정보 갱신이 이루어질 경우에 개별 경제주체는 새로운 정보를 바탕으로 합리적 기대 이론에서와 동일하게 기대대상 변수의 현재와 미래 경로 전체에 대한 기대를 수정하게 된다. 따라서 특정 시기의 평균기대는 현재의 정보와 다양한 시차의 과거 정보에 입각한 기대들의 가중합이 된다.",
  "summary": "Mankiw, Reis의 정보경직성 모형은 경제주체가 매기마다 일정 확률로 의사결정 필요 정보의 갱신 기회를 획득한다고 가정된다. 갱신 시 기대대상 변수의 현재, 미래 경로 전체 기대를 수정하게 된다."
}