{
  "passage_id": "PCY_201509210528050971_5",
  "metadata": {
    "doc_id": "PCY_201509210528050971",
    "doc_type": "도서",
    "doc_name": "육아정책포럼 제42호(겨울호)",
    "author": null,
    "publisher": "육아정책연구소\t",
    "published_year": "2014",
    "kdc_label": "유아및초·중등교육",
    "kdc_code": "300"
  },
  "chapter": null,
  "passage": "우리나라의 통계 생산 체제는 각 기관의 고유업무 수행을 위해 필요한 통계를 개별 기관책임 아래 작성하는 분산형 통계제도를 채택하고 있다. 국가승인통계 현황을 살펴보면, 2014년 6월 기준으로 389개 기관에서 922종의 승인통계가 작성되고 있다. 이 중 종류에 따라 지정통계 92종, 일반통계 830종이며, 작성방법별로는 조사통계 404종, 보고통계 445종, 가공통계 73종인 것으로 나타났다. 작성기관을 정부기관과 지정기관으로 구분하여 볼 때 정부기관에 의하여 작성되고 있는 통계는 755종(통계청은 58종)이며, 지정기관에서 작성하고 있는 통계는 167종이다(표 1 참조).",
  "summary": "우리나라는 분산형 통계제도를 사용하고 있다. 통계 현황을 보면 종류에 따라 지정통계, 일반통계로 나뉘며 작성방법별로는 조사통계, 보고통계, 가공통계로 나뉜다."
}