{
  "passage_id": "PCY_201702100510008871_3",
  "metadata": {
    "doc_id": "PCY_201702100510008871",
    "doc_type": "도서",
    "doc_name": "지진포커스. 통권6호",
    "author": null,
    "publisher": "기상청",
    "published_year": "2015",
    "kdc_label": "과학기술진흥",
    "kdc_code": "500"
  },
  "chapter": null,
  "passage": "최근 언론보도에 따르면 어느 지역 발전연구원에서 그 지역 대도시의 안전에 관한 시민 설문조사를 한 결과 그 도시에서 가장 우선적으로 대비해야 할 자연재난 중 ‘지진’이 응답률 33%로 가장 높게 나타났고 폭염(가뭄)과 풍수해 등이 그 뒤를 이었다고 한다. 지진이 다른 재난에 비해서 국내에 입히는 피해가 거의 없는데도 왜 이런 결과가 나왔을까. 그것은 이웃 일본 등 국제사회에서 발생하는 지진의 피해가 순식간에 놀라울 정도로 큰 규모로 벌어진다는 사실을 이미 인지를 하고 있는데다 지역 여건상 원자력발전소나 많은 산업시설이 운영되고 있는 터라 지진에 가장 먼저 우려의 시선을 보내지 않았나 싶다.",
  "summary": "대도시 안전 설문조사 결과, 지진 대비가 33%로 가장 높고, 폭염과 풍수해가 뒤를 이었다. 일본 등 국제 지진 피해 규모가 크고 원자력발전소나 많은 산업시설로 우려가 크다."
}