{
  "passage_id": "PCY_201705020504317351_34",
  "metadata": {
    "doc_id": "PCY_201705020504317351",
    "doc_type": "도서",
    "doc_name": "한-EU 문화협력위원회 핵심의제 개발연구",
    "author": null,
    "publisher": "한국문화관광연구원",
    "published_year": "2016",
    "kdc_label": "문화예술",
    "kdc_code": "600"
  },
  "chapter": null,
  "passage": "이를 반영하듯 2014년부터 현재 진행 중인 문화 프로그램의 명칭을‘Creative Europe’으로 명명하였다. 유럽의 미래를 이끌 창조의 원천으로 문화를 다루고 있음을 알 수 있다. 이 프로그램은 기존의 문화 프로그램(Culture Programme 2007-2013)과 이와 별도로 운영되던 시청각 프로그램(MEDIA 2007 Programme, MEDIA Mundus Programme)을 하나로 묶었다. 다시 말해 문화 프로그램과 두 시청각 프로그램을 ‘Creative Europe’이라는 하나의 틀에 담은 것이다(EACEA 2016). 대신 문화, 시청각, 교류 프로그램의 맥락은 각각의 세부 프로그램(sub-programme)으로 유지되어 지속된다. 다시 말해 이 프로그램은 시청각 프로그램, 문화프로그램, 교류 프로그램으로 구성된다.",
  "summary": "2014년부터 현재 진행 중인 문화 프로그램의 명칭을‘Creative Europe’으로 명명하였다. 문화 프로그램과 두 시청각 프로그램을 ‘Creative Europe’이라는 하나의 틀에 담은 것이다."
}