{
  "passage_id": "PCY_201806240352433491_75",
  "metadata": {
    "doc_id": "PCY_201806240352433491",
    "doc_type": "도서",
    "doc_name": "2017 산업재산권판례연구논문공모전우수 논문집",
    "author": null,
    "publisher": "특허청",
    "published_year": "2017",
    "kdc_label": "산업진흥·고도화",
    "kdc_code": "300"
  },
  "chapter": null,
  "passage": "미국 특허청의 심사기준에는 ‘Product-by-Process 청구항(이하 PbP 청구항이라고 함)은 비록 제조방법에 의해 한정 및 정의되어 있지만, 특허성 결정은 물건 그 자체에 의하고 물건의 제조방법에 의존하지 않는다. 만일 PbP 청구항의 물건이 선행기술의 물건과 동일하거나 그로부터 자명한 것이라면, 선행의 물건이 다른 방법으로 제조되었더라도 그 청구항은 특허받을 수 없다. 제조방법에 의해 암시되는 구조는, 특히 물건이 제조방법에 의해서만 특정될 수 있는 경우 또는 제조방법이 최종 제품에 독특한 구조적인 특성을 부여할 것으로 기대되는 경우, PbP 청구항의 특허성 판단에서 고려되어야 한다‘는 판단기준을 제시하고 있다.",
  "summary": "미 특허청의 결정은  pbp청구항은 물건 자체에 의하며, 물건이 선행 기술로부터 나왔거나, 그 것과 동일하다면, 선행 물건이 다르게 제조 되었어도 특허 받을 수 없다."
}