{
  "passage_id": "PCY_201907220452109411_28",
  "metadata": {
    "doc_id": "PCY_201907220452109411",
    "doc_type": "도서",
    "doc_name": "공공하수처리시설 운영관리계획서",
    "author": null,
    "publisher": "환경부,한국환경공단",
    "published_year": "2018",
    "kdc_label": "상하수도·수질",
    "kdc_code": "500"
  },
  "chapter": null,
  "passage": "역곡하수처리시설은 1단계 합류식지역, 2단계 분류식지역을 처리하는 시설로 설치되어 있는 하수처리시설이나 옥길지구의 택지지구가 완공되지 않아 현재는 1,2단계 통합운영을 하고 있으며 옥길지구가 완공되는 시점에 1단계와 2단계를 분리하여 운영할 계획이다. 본장은 강우시 발생되는 하수처리시설내의 문제점을 분석하여 강우시 안정적인 하수처리가 될 수 있도록 문제가 발생되는 시설에 대한 개선사항 및 대책을 제시하고 추가로 필요한 설비 등에 대해 검토하여 향후 시설 개선이 될 수 있도록 계획을 수립하였다. 또한, 역곡하수처리시설의 경우 하수처리시설 인근에 설치되어 있는 간이공공하수처리시설에 대한 문제점을 분석하여 향후 시설개선계획 수립시 참조할 수 있도록 제시하였다.",
  "summary": "잉여슬러지량 및 슬러지 계면을 상시 모니터링하여야 하여 생물반응조에 문제가 발생하지 않도록 운영하여야 한다."
}