{
  "passage_id": "PCY_201502110903522611_43",
  "metadata": {
    "doc_id": "PCY_201502110903522611",
    "doc_type": "도서",
    "doc_name": "감사논집(제21호)",
    "author": null,
    "publisher": "감사원",
    "published_year": null,
    "kdc_label": "국정운영",
    "kdc_code": "300"
  },
  "chapter": null,
  "passage": "본 연구는 새로운 원자력발전소가 건설 중에 있는 경북 경주 및 울진 지역에 거주하는 20세 이상의 남ㆍ여 258명을 대상으로 하여 그들이 인식하는 사회적 자본이 원전의 사회적 수용성에 미치는 영향을 살펴보았으며, 이 과정에서 투명성의 조절효과를 검증하였다. 본 연구의 자료분석을 위하여 PASW Statistics 18.0을 이용하였으며, 연구의 주요 결과는 다음과 같다. 첫째, 조사대상자가 인식하는 사회적 자본의 평균은 2.20(SD=.337)이었으며, 투명성은 2.45(SD=.521)로 조사되어 각각 보통 수준보다 낮은 것으로 나타났다. 둘째, 조사대상자들의 원전에 대한 사회적 수용성은 2.83(SD=.388)으로 조사되어 보통 수준보다 조금 낮은 것으로 나타났다. 조사대상자의 원전에 대한 사회적 수용성은 학력, 거주기간, 경제수준, 원전시설에 대한 설명회 참석, 원전시설의 견학 등에 따라 집단별로 통계적으로 유의미한 차이를 보였다. 셋째, 원전의 사회적 수용성에 미치는 영향을 알아보기 위해서 위계적 회귀분석을 실시한 결과, 조사대상자의 학력(p<.05), 거주기간(p<.05), 원전 견학경험(p<.05), 사회적 자본의 규범(p<.001)ㆍ대인신뢰(p<.05)ㆍ제도신뢰(p<.05), 투명성(p<.001)등이 영향을 미치는 것으로 조사되었으며, 투명성은 사회적 자본의 규범(p<.01) 및 제도신뢰(p<.01)와 상호작용하여 유의미한 조절효과를 갖는 것으로 나타났다. 이러한 연구결과를 기초로 하여 원전의 사회적 수용성을 제고하기 위한 몇 가지 방안을 제시하였다.",
  "summary": "원자력 발전소가 건설 중에 있는 경주 및 울진에 거주하는 20세 이상 남·여 258명을 대상으로 그들이 인식하는 사회적 자본이 원전의 사회적 수용성에 미치는 영향을 살펴본 결과, 사회적 자본 평균과 투명성은 보통 수준보다 낮고, 사회적 수용성은 조금 낮은 것으로 나타났으며, 조사대상자의 학력, 거주기간, 원전 견학경험, 사회적 자본의 규범, 제도신뢰, 투명성 등이 수용성에 영향을 미치는 것으로 조사되었다."
}