{
  "passage_id": "PCY_201707261103459671_75",
  "metadata": {
    "doc_id": "PCY_201707261103459671",
    "doc_type": "도서",
    "doc_name": "초고령사회 고령후기 노인을 위한 생애말기 정책 지원방안 연구",
    "author": "김경래",
    "publisher": "한국보건사회연구원",
    "published_year": "2016",
    "kdc_label": "노인·청소년",
    "kdc_code": "300"
  },
  "chapter": null,
  "passage": "인간이 죽음을 완전히 극복하기란 불가능하다. 하지만 지나친 공포를 정상적인 수준까지 완화할 필요는 있다. 죽음 교육에는 이처럼 극단적인 죽음의 공포를 완화하는 효과가 있다. 죽음을 자신에게 가까운 문제로 이해하고 삶과 죽음의 의의에 대해 배워 나가면서, 내면에 억압되어 있는 죽음의 공포가 어떤 것일까를 분명히 인식하게 되면 그 공포는 완화되기 시작한다. 호스피스 종사자의 경우에도 죽음에 직면한 당사자의 생사관에 따라 마음을 평안하게 유지하도록 권하는 태도, 그리고 마지막 순간까지 혼자가 아님을 깨닫게 해주는 보살핌이 중요하다고 한다(알폰스 데켄, 오진탁 역, 2002).",
  "summary": "인간은 죽음을 극복하기는 불가능하지만 죽음에 대한 지나친 공포를 갖을 필요는 없기에 죽음 교육을 통해 죽음 이해하고 극단적인 공포를 완화해야 한다."
}