{
  "passage_id": "PCY_201707060338381241_12",
  "metadata": {
    "doc_id": "PCY_201707060338381241",
    "doc_type": "도서",
    "doc_name": "문화재사랑 통권 제129호(2015년 08월)",
    "author": null,
    "publisher": "문화재청",
    "published_year": "2015",
    "kdc_label": "문화재",
    "kdc_code": "600"
  },
  "chapter": null,
  "passage": "외암마을 참판댁의 경우에서도 그와 같은 여성에 대한 배려 장치를 여럿 발견할 수 있다. 참판댁의 안채는 사랑채의 뒤에 위치해서 바깥사람들의 눈길에서 거의 완전하게 차단되어 있다. 대문간에서 집 안을 들여다보면 안채는 사랑채에 가려서 전혀 보이지 않는다. 사랑채의 측면에 위치한 안채 출입문도 대문간에서는 보이지 않게 되어 있었다. 그러면서도 안채 사람들이 바깥으로 출입할 수 있는 작은 문을 안채 출입문 곁에 따로 마련하여 출입의 편리를 도모하였다. 한층 더 여성을 배려한 장치는 협소한 안채에서의 살림을 보완하기 위해 만들어놓은 텃밭(참판댁에서는 이 텃밭을 남새밭으로 부른다.)과의 출입 통로이다. 참판댁에서는 이곳을 텃밭으로 사용하지만 많은 경우에 안채의 뒤뜰은 텃밭과 더불어 아름다운 수목을 심어서 자연을 접할 수 있게 하였다. 이를 통해서 외부출입이 제한된 삶의 답답함과 무료함을 달랠 수 있도록 하였다. 참판댁의 텃밭 출입 통로는 사랑채의 왼쪽 측면에 작은 쪽문으로 마련되어 있다. 사랑채의 옆이 바로 텃밭이기 때문에 이 쪽문을 통해서 바로 텃밭으로 출입할 수 있다. 더구나 이 텃밭은 큰집과 작은집 두 집으로 이루어진 참판댁의 작은집 안채 쪽문과 연결되어 있다. 따라서 큰집의 쪽문과 텃밭, 작은집의 안채는 외부인들의 눈길에서 벗어나 자유롭게 여성들이 공유하고 활용하는 공간이었던 셈이다. 결국 남녀유별의 질서를 따르면서도 집안사람들끼리 서로 편리하게 교류하고 텃밭에서 자연과 어울릴 수 있는 배려를 여기에서 함께 찾아볼 수 있다. 안동하회의 양진당養眞堂이나 충효당忠孝堂에도 외부인들은 쉽게 찾을 수 없는 안채와 사랑채 사이의 출입 통로가 있다. 이들은 모두 남녀유별이라는 당시의 사회적 가치를 존중하면서도 가족들 간의 실제적인 어울림과 소통을 배려한 장치로 이해할 수 있다.",
  "summary": "여성을 배려하기 위해 안채는 외부에서 보이지 않도록 가려져 있지만 출입은 편리하게 만들었다. 더 여성을 배려하는 것은 텃밭으로 안채의 뒤뜰과 텃밭은 아름다운 수목으로 자연을 접할 수 있고 삶의 답답함을 해소한다. 큰집의 쪽문과 텃밭, 작은집의 안채는 여성들의 자유로운 활용 공간이다. 안동하회의 양진당이나 충효당에도 안채와 사랑채 사이에 출입통로가 있어 외부인들에게 노출되지 않는데 이는 남녀유별의 사회적 가치를 존중함과 동시에 가족의 어울림과 소통을 위한 장치로 활용되었다."
}