{
  "passage_id": "PCY_201508260207431001_24",
  "metadata": {
    "doc_id": "PCY_201508260207431001",
    "doc_type": "도서",
    "doc_name": "영아보육 질 제고를 위한 평가도구 개발 및 활용방안",
    "author": null,
    "publisher": "육아정책연구소\t",
    "published_year": null,
    "kdc_label": "유아및초·중등교육",
    "kdc_code": "300"
  },
  "chapter": "영아평가 실태 및 요구분석",
  "passage": "교사의 최종학력을 살펴보면, 보육교사 교육원을 수료한 교사는 182명(29%), 전문대학(2~3년제)을 졸업한 교사는 302명(48.4%), 4년제 대학 이상 졸업은 140명(22.4%)이었다(표 Ⅰ-3-2, p.14 참조). 요구조사에 응답한 교사의 총 경력은 5년 이상이 30.4%로 가장 많았고, 1~3년 미만(27.9%), 1년 미만(26.6%)의 순이었고, 영아반 경력은 1년 미만(34.5%)이 가장 많았고, 3년 이상(27.7%), 1~2년 미만(21.3%)의 순이었다. 교사연령은 40대 이상이 269명(43.1%)로 가장 많았고, 30대가 214명(34.3%), 20대가 141명(22.6%)이었다.",
  "summary": "교사의 최종학력은 전문대학을 졸업한 수가 가장 많았고 교육원, 4년제이상 순이었으며 요구조사에 응답한 교사의 총 경력은 5년이상이 가장 많았으며 연령은 40대 이상이 가장 많았다."
}