{
  "passage_id": "PCY_201707270120494911_43",
  "metadata": {
    "doc_id": "PCY_201707270120494911",
    "doc_type": "도서",
    "doc_name": "문화재사랑 통권 제140호(2016년 07월)",
    "author": null,
    "publisher": "문화재청",
    "published_year": "2016",
    "kdc_label": "문화재",
    "kdc_code": "600"
  },
  "chapter": null,
  "passage": "자연스레 그가 관심을 갖고 객관적인 시선으로 연구를 시작한 ‘신미양요’. 미국인이지만 신미양요의 전쟁사적 측면을 보편적이고 객관적인 입장으로 접근했다. 현재 병인양요에 대해서도 관심을 갖고 연구를 계획하고 있는 토마스 듀버네이 교수는 수시로 강화도를 찾는다. 역사의 산물이라 할 수 있는 강화도에서 무분별하고 빠르게 진행되고 있는 개발에 그는 마음이 급하다. “개발을 피할 수는 없어요. 그렇다고 손 놓고 있을 수는 없습니다. 한번 개발이 되고 나면 그전으로의 복구는 힘들어져요. 개발을 진행하기에 앞서 신중할 필요가 있으며, 한시라도 빨리 역사적으로 가치가 있는 장소의 경우 발굴하고 현장을 기록하는 노력이 선행되어야 합니다.”",
  "summary": "토마스 듀버네이 교수는 수시로 강화도를 찾는다. 역사의 산물이라 할 수 있는 강화도에서 무분별하고 빠르게 진행되고 있는 개발에 그는 마음이 급하다."
}