{
  "passage_id": "PCY_201610200103451461_22",
  "metadata": {
    "doc_id": "PCY_201610200103451461",
    "doc_type": "도서",
    "doc_name": "중저기술 산업의 혁신특성 분석과 발전방향",
    "author": null,
    "publisher": "과학기술정책연구원",
    "published_year": "2015",
    "kdc_label": "과학기술진흥",
    "kdc_code": "500"
  },
  "chapter": null,
  "passage": "김병기(2008)의 연구에서는 1999년 ~ 2005년 기간 동안 기업데이터를 통해 R&D투자와 기업 간의 관계를 분석한 결과 전반적으로 기업의 R&D집중도(매출액/연구개발비로 측정)가 높을수록 기업가치는 상승하였음 확인하였다. 그리고 첨단산업군 여부에 따라 일부 차이가 확인되었는데 첨단산업군에 속한 기업들은 R&D집중도가 높을수록 기업의 가치가 상승하고 있지만, 비첨단산업군에 속한 기업들에게서는 이러한 관계가 존재하지 않는 것으로 분석되었다. 따라서 중저기술기업의 경우 R&D 지원을 늘려 R&D 집중도를 향상시키는 것이 기업의 혁신활동에 도움이 된다고 보기 어려움을 알 수 있다. 즉, 중저기술산업의 R&D 비중을 늘려 고기술산업화하는 것이 해당 산업을 발전시키는데 반드시 필요한 지원책이 아닐 수 있음을 보였다고 볼 수 있다.",
  "summary": "첨단산업군에 속한 기업일 수록 R&D집중도가 높고 기업의 가치도 상승한 반면 비첨단군에 속한 기업들에서는 상관 관계가 없으므로 중저기술기업에 R&D지원으로 R&D 집중도를 높이는 것만이 고기술산업화로의 정책은 아니다."
}