{
  "passage_id": "PCY_201509030205241441_33",
  "metadata": {
    "doc_id": "PCY_201509030205241441",
    "doc_type": "도서",
    "doc_name": "세대별, 성별 1인 가구의 고용과 가구경제 연구",
    "author": null,
    "publisher": "한국여성정책연구원\t",
    "published_year": null,
    "kdc_label": "보육·가족및여성",
    "kdc_code": "300"
  },
  "chapter": null,
  "passage": "두 번째 향후 과제는 균등화에 대한 이슈이다. 현재까지 사용하는 균등화 방법에 대한 비판적 고찰이 필요하다. 1인 가구가 갖는 이질성을 볼 때 가구 균등화 지수를 이용한 2인 이상 가구와의 비교는 1인 가구의 특성을 정확하게 반영하지 못할 가능성이 크다. 본 연구의 분석에서도 취업상태의 변화에 따른 소득 변화들을 볼 때 규모와 분포에 있어서 1인 가구의 모습은 전체 가구와 상당히 다르게 나타나고 있고 여러 가지 분석결과에서 비일관된 모습을 보이기도 하였다. 다른 요인들을 통제했을 때 1인 가구의 취업상태 변화에 따른 소득변화에서 여성 1인 가구만이 민감하게 반응하는 것으로 나타날 뿐 남성 1인 가구에서는 이러한 현상들이 잘 나타나지 않는다. 물론 다른 요인들이 복합적으로 영향을 미치기 때문이기도 하지만 균등화 방식에 따른 문제일 가능성도 배제할 수 없다. 향후 보편적인 가구형태로 자리 잡을 1인 가구의 경제적 상태 분석을 위해 다양한 방법론의 개발이 요구됨을 알 수 있다.",
  "summary": "1인 가구의 취업상태 변화에 따른 소득 변화는 전체 가구와 다르게 나타난다. 2인 이상 가구와의 비교는 1인 가구의 특성을 정확하게 반영하지 못하고 복합적 요인들로 인한 균등화 문제 등이 있기에 향후 1인 가구 경제 상태 분석을 위한 다양한 방법론 개발이 요구된다."
}