{
  "passage_id": "PCY_201412011009271251_101",
  "metadata": {
    "doc_id": "PCY_201412011009271251",
    "doc_type": "도서",
    "doc_name": "국토: 2014년 11월 (통권397호)",
    "author": null,
    "publisher": "국토연구원",
    "published_year": "2014",
    "kdc_label": "지역및도시",
    "kdc_code": "300"
  },
  "chapter": null,
  "passage": "이렇게 작은 규모로 운영되고는 있지만, 리모트센싱 분야의 학술 진흥을 위해 일본에서 유일하게 인터넷으로 위성정보를 무료로 제공하고 있다. 이를 바탕으로 타 대학 및 연구소와 40여 건(2013년 기준)의 공동연구를 수행하고 있다. 이렇게 무료로 제공되는 위성정보의 다운로드 건수, 공동연구 건수, 출판논문 건수 등은 그대로 문부과학성의 대학평가에 반영된다. 실제로 ‘국립대학 공동이용/공동연구 거점협의회’에 소속된 CEReS는 위성정보 무상 공유(다운로드) 건수를 매년 문부과학성에 보고하고 있다. 이러한 특성화 노력의 일환으로 2010년 4월 문부과학성의 ‘국립대학 제2기 중기 계획’에 의거하여 ‘환경원격탐사 분야 공동 이용 및 연구 거점’으로 선정되기도 하였다. 그러나 여전히 운영비 충당을 위해 소속 교수들은 외부 연구과제를 적극적으로 수주하려고 노력하고 있으며, 대부분의 과제는 JAXA가 발주한 사업들이다.",
  "summary": "리모트센싱 분야의 학술진흥을 위해 무료 위성 정보를 인터넷으로 제공하며, 이를 바탕으로 40여건의 공동연구를 수행하고 있다. 결과물은 문부과학성의 대학 평가에 반영되어  ‘환경원격탐사 분야 공동 이용 및 연구 거점’으로 선정되었다."
}