{
  "passage_id": "PCY_201501270959144541_21",
  "metadata": {
    "doc_id": "PCY_201501270959144541",
    "doc_type": "도서",
    "doc_name": "초·중학교 교수학습 연계 지원 방안 탐색",
    "author": null,
    "publisher": "한국교육과정평가원",
    "published_year": "2014",
    "kdc_label": "유아및초·중등교육",
    "kdc_code": "300"
  },
  "chapter": null,
  "passage": "둘째, 호주의 통합학교(composed schools)는 주에 따라 다른 명칭을 사용하고 있는데, 농어촌 지역에 주로 위치하고 있는 통합학교는 지역의 인구 감소에 따라 학교가 통폐합된 결과로 나타나고 있다. 호주의 통합학교는 일반학교가 가지지 못한 장점을 가지고 있다. 예를 들어, 통합학교 학생들은 오랜 기간 동안 동일한 울타리에서 생활할 수 있어서 일반학교 학생들이 상급학교 진학에 따라 공통적으로 겪게 되는 새로운 적응과 탐색에 따른 긴장과 불안감을 상대적으로 낮게 경험하게 된다. 또한 학생의 성장 및 발달 과정에 대한 이력 관리와 정보 공유가 유리하여 교사들은 학생 지도에 따른 시행착오를 줄여 효과적으로 학생을 지도할 가능성이 높다.",
  "summary": "호주의 통합학교는 일반학교와 달리 진학시 적응과 탐색에 따른 긴장과 불안감 경험이 낮다. 또한 학생의 성장 및 발달 과정 이력 관리와 정보 공유가 유리해 교사들의 지도적 시행착오를 줄여준다."
}