{
  "passage_id": "PCY_201906060826192161_10",
  "metadata": {
    "doc_id": "PCY_201906060826192161",
    "doc_type": "도서",
    "doc_name": "국어 발전과 보전에 관한 시책 및 시행 결과 보고서(2017) : 2018 정기국회 보고 자료",
    "author": null,
    "publisher": "문화체육관광부",
    "published_year": "2018",
    "kdc_label": "문화예술",
    "kdc_code": "600"
  },
  "chapter": null,
  "passage": "한편, 국가 차원에서 한국어의 언어문화 정보와 지식을 수집하여 통합 관리하고, 활용을 지원하기 위해  우리말샘을 운영하고 있다. 이를 통하여 실생활에서 쓰이고 있는 한국어 자료를 110만 단어 규모로 수집 관리 제공하여 사용자의 언어생활 편의성을 높이고, 민간 특화 사전 개발 및 문화 콘텐츠의 핵심 요소로 활용할 수 있도록 지원하고 있다. 특히 21세기 세종계획 등 국어 정보 처리 성과물의 통합 관리 및 배포 체계인 ‘언어 정보 나눔터’를 통하여 대용량 언어 자료 및 활용 도구를 보급하고 있다. 또한 소멸 위기에 처한 방언 음성 자료를 조사하여 통합 데이터 베이스로 구축하는 등 한국어 음성 자료의 디지털화를 수행하고 있다.",
  "summary": "국가 차원에서 한국어 자료를 수집하고 관리, 활용하기 위해 우리말샘을 운영한다. 언어 정보 나눔터를 통해 대용량 언어 자료를 보급하고 있으며 방언 자료를 조사하여 디지털화하고 있다."
}