{
  "passage_id": "PCY_201709130902579691_63",
  "metadata": {
    "doc_id": "PCY_201709130902579691",
    "doc_type": "도서",
    "doc_name": "청소년이 행복한 지역사회 지표개발 및 조성사업 연구Ⅲ : ‘청소년이 행복한 지역사회 조성 시범사업’ 운영과 추진전략 개발",
    "author": "오해섭",
    "publisher": "한국청소년정책연구원",
    "published_year": "2015",
    "kdc_label": "노인·청소년",
    "kdc_code": "300"
  },
  "chapter": null,
  "passage": "아동․청소년관련 예산의 수립은 각 지역에서의 자원을 활용하는 것뿐만 아니라 중앙정부와의 협의도 필요하다. 또한 예산 수립의 기준에는 취약계층 아동․청소년을 위한 예산 확보와 집행을 어느 정도 포함하고 있는지도 고려되어야 할 것이다. 교육이나 보건의 문제에 있어서의 예산 할당은 주로 중앙정부가 결정하므로 이 안에서 지방정부는 불평등과 차별을 최소화하기 위한 자원 배분에 있어 공정하게 집행할 수 있어야 한다. 예산의 확보와 집행‚ 수립은 아동․청소년을 포함한 지역의 모든 구성원에게 공개되고 검증되는 것이 원칙이다(UNICEF‚ 2015).",
  "summary": "아동 청소년 예산에는 취약계층도 고려돼야 한다. 교육 보건 예산은 지방정부의 공정 집행이 필요하며 확보, 집행‚ 수립은 지역 전 구성원에 공개 검증을 해야한다."
}